datadoglog/__init__.py
datadoglog/formatter.py
datadoglog/init.py
datadog_log-1.5.1.dist-info/LICENSE
datadog_log-1.5.1.dist-info/METADATA
datadog_log-1.5.1.dist-info/WHEEL
datadog_log-1.5.1.dist-info/RECORD
