Metadata-Version: 2.1
Name: datadog-log
Version: 1.5.1
Summary: JSON formatted logging for Datadog
Home-page: https://github.com/mindhivenz/datadog-log-py
License: MIT
Author: Mindhive devs
Author-email: devops@mindhive.co.nz
Requires-Python: >=3.8,<4.0
Classifier: License :: OSI Approved :: MIT License
Classifier: Programming Language :: Python :: 3
Classifier: Programming Language :: Python :: 3.8
Classifier: Programming Language :: Python :: 3.9
Classifier: Programming Language :: Python :: 3.10
Classifier: Programming Language :: Python :: 3.11
Classifier: Programming Language :: Python :: 3.12
Requires-Dist: python-json-logger (>=2,<3)
Project-URL: Repository, https://github.com/mindhivenz/datadog-log-py
